codepub/__init__.py
codepub/functions.py
codepub/functions_before.py
codepub/test.py
codepub/data/10n_1X_10M.txt
codepub/data/10n_2X_45M.txt
codepub/data/10n_3X_120M.txt
codepub/data/10n_4X_193M.txt
codepub/data/10n_5X_193M.txt
codepub/data/10n_6X_100M.txt
codepub/data/10n_7X_45M.txt
codepub/data/11n_1X_11M.txt
codepub/data/11n_2X_55M.txt
codepub/data/11n_3X_165M.txt
codepub/data/11n_4X_313M.txt
codepub/data/11n_5X_390M.txt
codepub/data/11n_6X_293M.txt
codepub/data/11n_7X_145M.txt
codepub/data/12n_1X_12M.txt
codepub/data/12n_2X_66M.txt
codepub/data/12n_3X_220M.txt
codepub/data/12n_4X_478M.txt
codepub/data/12n_5X_703M.txt
codepub/data/12n_6X_710M.txt
codepub/data/12n_7X_438M.txt
codepub/data/12n_8X_205M.txt
codepub/data/13n_1X_13M.txt
codepub/data/13n_2X_78M.txt
codepub/data/13n_3X_286M.txt
codepub/data/13n_4X_698M.txt
codepub/data/13n_5X_1181M.txt
codepub/data/13n_6X_1413M.txt
codepub/data/13n_7X_1148M.txt
codepub/data/13n_8X_643M.txt
codepub/data/14n_1X_14M.txt
codepub/data/14n_2X_91M.txt
codepub/data/14n_3X_364M.txt
codepub/data/14n_4X_984M.txt
codepub/data/14n_5X_1879M.txt
codepub/data/14n_6X_2594M.txt
codepub/data/14n_7X_2561M.txt
codepub/data/14n_8X_1791M.txt
codepub/data/15n_1X_15M.txt
codepub/data/15n_2X_105M.txt
codepub/data/15n_3X_455M.txt
codepub/data/15n_4X_1348M.txt
codepub/data/15n_5X_2863M.txt
codepub/data/15n_6X_4473M.txt
codepub/data/15n_7X_5155M.txt
codepub/data/15n_8X_4352M.txt
codepub/data/16n_1X_16M.txt
codepub/data/16n_2X_120M.txt
codepub/data/16n_3X_560M.txt
codepub/data/16n_4X_1803M.txt
codepub/data/16n_5X_4211M.txt
codepub/data/16n_6X_7336M.txt
codepub/data/16n_7X_9628M.txt
codepub/data/16n_8X_9507M.txt
codepub/data/17n_1X_17M.txt
codepub/data/17n_2X_136M.txt
codepub/data/17n_3X_680M.txt
codepub/data/17n_4X_2363M.txt
codepub/data/17n_5X_6014M.txt
codepub/data/17n_6X_11547M.txt
codepub/data/17n_7X_16964M.txt
codepub/data/17n_8X_19135M.txt
codepub/data/18n_1X_18M.txt
codepub/data/18n_2X_153M.txt
codepub/data/18n_3X_816M.txt
codepub-2.3.dist-info/METADATA
codepub-2.3.dist-info/WHEEL
codepub-2.3.dist-info/licenses/LICENSE
codepub-2.3.dist-info/RECORD
