Metadata-Version: 2.4
Name: codepub
Version: 2.3
Summary: CodePUB
Project-URL: Homepage, https://codepub.readthedocs.io/en/latest/index.html
Project-URL: Bug Tracker, https://github.com/meyer-lab-cshl/codepub/issues
Author-email: Vasilisa Kovaleva <vasilisa.kovaliova@gmail.com>, Guanchen He <hgc01@buaa.edu.cn>
License-File: LICENSE
Classifier: License :: OSI Approved :: BSD License
Classifier: Operating System :: OS Independent
Classifier: Programming Language :: Python :: 3
Requires-Python: >=3.7
Requires-Dist: numpy>=1.23.5
